ncuhep/__init__.py
ncuhep/job_scheduler/__init__.py
ncuhep/job_scheduler/smart_pause.py
ncuhep/job_scheduler/smart_scheduler.py
ncuhep/muography/__init__.py
ncuhep/muography/classes/__init__.py
ncuhep/muography/classes/analysis_config.py
ncuhep/muography/classes/mu_txt_format.py
ncuhep/muography/classes/plane_detector.py
ncuhep/muography/data_processing/__init__.py
ncuhep/muography/data_processing/data_processing.py
ncuhep/muography/data_processing/gui.py
ncuhep/muography/demviewer/__init__.py
ncuhep/muography/demviewer/__main__.py
ncuhep/muography/demviewer/dem_utils.py
ncuhep/muography/demviewer/properties.py
ncuhep/muography/demviewer/resources.py
ncuhep/muography/demviewer/settings_dialog.py
ncuhep/muography/demviewer/startup.py
ncuhep/muography/demviewer/viewer.py
ncuhep/muography/demviewer/data/DEM_20m.npz
ncuhep/muography/demviewer/data/__init__.py
ncuhep/muography/demviewer/data/muography_icon.png
ncuhep/muography/demviewer/data/startup_sound.wav
ncuhep/muography/demviewer/data/viewer_settings.json
ncuhep/muography/identifier/__init__.py
ncuhep/muography/identifier/identifier.py
ncuhep/muography/mc_renderer/__init__.py
ncuhep/muography/mc_renderer/monte_carlo.py
ncuhep/muography/muonscatter/__init__.py
ncuhep/muography/muonscatter/angle.py
ncuhep/muography/muonscatter/calculate.py
ncuhep/muography/muonscatter/constants.py
ncuhep/muography/muonscatter/constructor.py
ncuhep/muography/muonscatter/flux_model.py
ncuhep/muography/muonscatter/gpu.py
ncuhep/muography/muonscatter/moliere.py
ncuhep/muography/muonscatter/predictors/4bivpoly_param0.npz
ncuhep/muography/muonscatter/predictors/4bivpoly_param1.npz
ncuhep/muography/muonscatter/predictors/4bivpoly_param2.npz
ncuhep/muography/muonscatter/predictors/4bivpoly_param3.npz
ncuhep/muography/muonscatter/predictors/4bivpoly_param4.npz
ncuhep/muography/muonscatter/predictors/4bivpoly_param5.npz
ncuhep/muography/muonscatter/predictors/4bivpoly_param6.npz
ncuhep/muography/muonscatter/predictors/Moliere_A_predictor.npz
ncuhep-0.2.23.dist-info/licenses/LICENSE
ncuhep-0.2.23.dist-info/METADATA
ncuhep-0.2.23.dist-info/WHEEL
ncuhep-0.2.23.dist-info/top_level.txt
ncuhep-0.2.23.dist-info/RECORD
