Metadata-Version: 2.4
Name: ncuhep
Version: 0.2.23
Summary: NCU High Energy Physics tools for muography and related analysis.
Author: Phay Kah Seng
Author-email: phay_ks@icloud.com
License: NCUHEP Research License (see LICENSE)
Classifier: Programming Language :: Python :: 3
Classifier: License :: Other/Proprietary License
Classifier: Intended Audience :: Science/Research
Classifier: Topic :: Scientific/Engineering :: Physics
Requires-Python: >=3.11
License-File: LICENSE
Requires-Dist: opencv-python
Requires-Dist: numpy
Requires-Dist: scipy
Requires-Dist: iminuit
Requires-Dist: matplotlib==3.9.4
Requires-Dist: tqdm
Requires-Dist: numba==0.62.0rc2
Requires-Dist: pandas
Requires-Dist: psutil
Requires-Dist: PyQt6
Requires-Dist: PyQt5
Requires-Dist: daemonflux
Requires-Dist: pyqtgraph
Requires-Dist: PyOpenGL
Requires-Dist: PyOpenGL-accelerate
Dynamic: author
Dynamic: author-email
Dynamic: classifier
Dynamic: description
Dynamic: description-content-type
Dynamic: license
Dynamic: license-file
Dynamic: requires-dist
Dynamic: requires-python
Dynamic: summary
